TG_Rate_95CI.py
__init__.py
TG_Rate_95CI-1.0.0.dist-info/LICENSE
TG_Rate_95CI-1.0.0.dist-info/METADATA
TG_Rate_95CI-1.0.0.dist-info/WHEEL
TG_Rate_95CI-1.0.0.dist-info/top_level.txt
TG_Rate_95CI-1.0.0.dist-info/RECORD
