Metadata-Version: 2.1
Name: TG-Rate-95CI
Version: 1.0.0
Summary: Calculating the 95% confidence interval for the trend of Tide Gauge data
Author-email: "Guoquan (Bob) Wang" <bob.g.wang@gmail.com>
License: The MIT License (MIT)
Project-URL: Homepage, https://github.com/bob-Github-2020/TG_Rate_95CI
Classifier: License :: OSI Approved :: MIT License
Classifier: Programming Language :: Python
Classifier: Programming Language :: Python :: 3
Requires-Python: >=3.8
License-File: LICENSE
